demo/demo1.py
demo/demo2.py
demo/test.py
lite_taskman/__init__.py
lite_taskman/core.py
lite_taskman-0.9.1.dist-info/LICENSE
lite_taskman-0.9.1.dist-info/METADATA
lite_taskman-0.9.1.dist-info/WHEEL
lite_taskman-0.9.1.dist-info/top_level.txt
lite_taskman-0.9.1.dist-info/RECORD
