Metadata-Version: 2.1
Name: lite-taskman
Version: 0.9.1
Summary: A lightweight thread pool manager supporting dynamic task addition and streaming results.
Author-email: Rocks Wang <rockswang@foxmail.com>
License: MIT
Project-URL: Homepage, https://github.com/rockswang/lite-taskman
Keywords: threadpool,task-manager,dynamic,lightweight,concurrency
Classifier: Development Status :: 4 - Beta
Classifier: Intended Audience :: Developers
Classifier: License :: OSI Approved :: MIT License
Classifier: Operating System :: OS Independent
Classifier: Programming Language :: Python :: 3
Classifier: Programming Language :: Python :: 3.8
Classifier: Programming Language :: Python :: 3.9
Classifier: Programming Language :: Python :: 3.10
Classifier: Programming Language :: Python :: 3.11
Classifier: Programming Language :: Python :: 3.12
Classifier: Topic :: Software Development :: Libraries :: Python Modules
Classifier: Topic :: Utilities
Requires-Python: >=3.7
License-File: LICENSE
